<?xml version="1.0" encoding="utf-8" ?><dwsync><file name="bootstrap-datetimepicker.bg.js" server="dove.arvixe.com" local="3459081840" remote="12053543312" /><file name="bootstrap-datetimepicker.cs.js" server="dove.arvixe.com" local="3459081840" remote="12053543312" /><file name="bootstrap-datetimepicker.da.js" server="dove.arvixe.com" local="3459081840" remote="12053543312" /><file name="bootstrap-datetimepicker.de.js" server="dove.arvixe.com" local="3459081840" remote="12053543312" /><file name="bootstrap-datetimepicker.es.js" server="dove.arvixe.com" local="3459081840" remote="12053543372" /><file name="bootstrap-datetimepicker.fa-IR.js" server="dove.arvixe.com" local="3459081840" remote="12053543372" /><file name="bootstrap-datetimepicker.fi.js" server="dove.arvixe.com" local="3459081840" remote="12053543372" /><file name="bootstrap-datetimepicker.fo.js" server="dove.arvixe.com" local="3459081840" remote="12053543372" /><file name="bootstrap-datetimepicker.fr.js" server="dove.arvixe.com" local="3459081840" remote="12053543372" /><file name="bootstrap-datetimepicker.hr.js" server="dove.arvixe.com" local="3459081840" remote="12053543372" /><file name="bootstrap-datetimepicker.hu.js" server="dove.arvixe.com" local="3459081840" remote="12053543372" /><file name="bootstrap-datetimepicker.id.js" server="dove.arvixe.com" local="3459081840" remote="12053543372" /><file name="bootstrap-datetimepicker.is.js" server="dove.arvixe.com" local="3459081840" remote="12053543372" /><file name="bootstrap-datetimepicker.it.js" server="dove.arvixe.com" local="3459081840" remote="12053543372" /><file name="bootstrap-datetimepicker.ja.js" server="dove.arvixe.com" local="3459081840" remote="12053543372" /><file name="bootstrap-datetimepicker.kr.js" server="dove.arvixe.com" local="3459081840" remote="12053543372" /><file name="bootstrap-datetimepicker.lt.js" server="dove.arvixe.com" local="3459081840" remote="12053543372" /><file name="bootstrap-datetimepicker.lv.js" server="dove.arvixe.com" local="3459081840" remote="12053543372" /><file name="bootstrap-datetimepicker.ms.js" server="dove.arvixe.com" local="3459081840" remote="12053543372" /><file name="bootstrap-datetimepicker.nb.js" server="dove.arvixe.com" local="3459081840" remote="12053543372" /><file name="bootstrap-datetimepicker.nl.js" server="dove.arvixe.com" local="3459081840" remote="12053543372" /><file name="bootstrap-datetimepicker.pl.js" server="dove.arvixe.com" local="3459081840" remote="12053543372" /><file name="bootstrap-datetimepicker.pt-BR.js" server="dove.arvixe.com" local="3459081840" remote="12053543432" /><file name="bootstrap-datetimepicker.pt.js" server="dove.arvixe.com" local="3459081840" remote="12053543432" /><file name="bootstrap-datetimepicker.ro.js" server="dove.arvixe.com" local="3459081840" remote="12053543432" /><file name="bootstrap-datetimepicker.rs-latin.js" server="dove.arvixe.com" local="3459081840" remote="12053543432" /><file name="bootstrap-datetimepicker.rs.js" server="dove.arvixe.com" local="3459081840" remote="12053543432" /><file name="bootstrap-datetimepicker.ru.js" server="dove.arvixe.com" local="3459081840" remote="12053543432" /><file name="bootstrap-datetimepicker.sk.js" server="dove.arvixe.com" local="3459081840" remote="12053543432" /><file name="bootstrap-datetimepicker.sl.js" server="dove.arvixe.com" local="3459081840" remote="12053543432" /><file name="bootstrap-datetimepicker.sv.js" server="dove.arvixe.com" local="3459081840" remote="12053543432" /><file name="bootstrap-datetimepicker.th.js" server="dove.arvixe.com" local="3459081840" remote="12053543432" /><file name="bootstrap-datetimepicker.tr.js" server="dove.arvixe.com" local="3459081840" remote="12053543432" /><file name="bootstrap-datetimepicker.zh-CN.js" server="dove.arvixe.com" local="3459081840" remote="12053543432" /><file name="bootstrap-datetimepicker.zh-TW.js" server="dove.arvixe.com" local="3459081840" remote="12053543432" /></dwsync>